LICENSE
LICENSE.txt
MANIFEST.in
README.md
setup.cfg
setup.py
taskmonk/BatchStatus.py
taskmonk/Pydoc.py
taskmonk/TaskMonkClient.py
taskmonk/__init__.py
taskmonk/utils/__init__.py
taskmonk/utils/apiCall.py
taskmonk/utils/argumentlist.py
taskmonk/utils/jsonUtils.py
taskmonk/utils/urlConfig.py
taskmonk/utils/utilities.py
taskmonk_sdk.egg-info/PKG-INFO
taskmonk_sdk.egg-info/SOURCES.txt
taskmonk_sdk.egg-info/dependency_links.txt
taskmonk_sdk.egg-info/requires.txt
taskmonk_sdk.egg-info/top_level.txt